{"name": "Avalanche", "symbol": "AVAX", "description": "Avalanche is a high throughput smart contract blockchain\u00a0platform. Validators secure the network through a proof-of-stake consensus protocol. It is said to be fast, low cost, and environmental friendly.", "image": "https://coin-images.coingecko.com/coins/images/12559/large/Avalanche_Circle_RedWhite_Trans.png?1696512369", "current_price": 29.26, "market_cap": 12302135097, "total_volume": 1588290081, "high_24h": 29.89, "low_24h": 27.18, "price_change_percentage_24h": -0.97753, "price_change_percentage_7d": -14.01312, "price_change_percentage_30d": 17.12428, "last_updated": "2025-09-26T17:34:02.914Z"}